LICENSE.md
README.md
setup.cfg
setup.py
popupsort/__init__.py
popupsort/popupsort.py
popupsort.egg-info/PKG-INFO
popupsort.egg-info/SOURCES.txt
popupsort.egg-info/dependency_links.txt
popupsort.egg-info/not-zip-safe
popupsort.egg-info/top_level.txt