Metadata-Version: 2.1
Name: popupsort
Version: 1.5.3
Summary: A Python package for visualizing sorting algorithms
Home-page: https://github.com/ZouheirN/PopUpSort
Author: Zouheir Nakouzi
Author-email: zouheir2002@gmail.com
License: MIT
Platform: UNKNOWN
